pandoraaperture/__init__.py
pandoraaperture/data/pandora.mplstyle
pandoraaperture/docstrings.py
pandoraaperture/fits.py
pandoraaperture/prf.py
pandoraaperture/scene.py
pandoraaperture/utils.py
pandoraaperture-0.1.14.dist-info/METADATA
pandoraaperture-0.1.14.dist-info/WHEEL
pandoraaperture-0.1.14.dist-info/licenses/LICENSE
pandoraaperture-0.1.14.dist-info/RECORD
